frame_sdk/__init__.py
frame_sdk/bluetooth.py
frame_sdk/camera.py
frame_sdk/display.py
frame_sdk/files.py
frame_sdk/frame.py
frame_sdk/library_functions.py
frame_sdk/microphone.py
frame_sdk/motion.py
frame_sdk-1.2.4.dist-info/METADATA
frame_sdk-1.2.4.dist-info/WHEEL
frame_sdk-1.2.4.dist-info/RECORD
