Metadata-Version: 2.4
Name: frame-sdk
Version: 1.2.4
Summary: Python Developer SDK for Brilliant Frame glasses
Project-URL: Homepage, https://github.com/brilliantlabsAR/frame-sdk-python
Project-URL: Bug Tracker, https://github.com/brilliantlabsAR/frame-sdk-python/issues
Author-email: Roger Pincombe <pip@betechie.com>, Brilliant Labs <info@brilliant.xyz>
License: MIT License
Classifier: Operating System :: OS Independent
Classifier: Programming Language :: Python :: 3
Requires-Python: >=3.7
Requires-Dist: bleak
Requires-Dist: exif
Requires-Dist: numpy
Requires-Dist: simpleaudio
